bilauth/__init__.py
bilauth/main.py
bilauth-0.2.1.dist-info/licenses/License
bilauth-0.2.1.dist-info/METADATA
bilauth-0.2.1.dist-info/WHEEL
bilauth-0.2.1.dist-info/top_level.txt
bilauth-0.2.1.dist-info/RECORD
